{
  "category": "music",
  "name": "Âm nhạc",
  "emoji": "🎵",
  "questions": [
    {"id": "music_001", "q": "Michael Jackson được mệnh danh là gì?", "o": ["Vua nhạc Rock", "Vua nhạc Pop", "Vua nhạc Soul", "Hoàng tử nhạc Blues"], "a": 1, "difficulty": 1},
    {"id": "music_002", "q": "Guitar thông thường có bao nhiêu dây?", "o": ["4", "5", "6", "7"], "a": 2, "difficulty": 1},
    {"id": "music_003", "q": "Nhạc sĩ nào sáng tác bản 'Moonlight Sonata'?", "o": ["Mozart", "Bach", "Chopin", "Beethoven"], "a": 3, "difficulty": 1},
    {"id": "music_004", "q": "'BTS' là nhóm nhạc đến từ quốc gia nào?", "o": ["Nhật Bản", "Trung Quốc", "Hàn Quốc", "Thái Lan"], "a": 2, "difficulty": 1},
    {"id": "music_005", "q": "Album bán chạy nhất lịch sử là album nào?", "o": ["Thriller - Michael Jackson", "Back in Black - AC/DC", "The Dark Side of the Moon - Pink Floyd", "Eagles - Their Greatest Hits"], "a": 0, "difficulty": 1},
    {"id": "music_006", "q": "Nốt nhạc nào có giá trị dài nhất trong ký hiệu nhạc thông thường?", "o": ["Đen (Quarter)", "Trắng (Half)", "Tròn (Whole)", "Móc đơn (Eighth)"], "a": 2, "difficulty": 1},
    {"id": "music_007", "q": "'The Beatles' có bao nhiêu thành viên?", "o": ["3", "4", "5", "6"], "a": 1, "difficulty": 1},
    {"id": "music_008", "q": "Nhạc cụ nào là biểu tượng của nhạc Jazz?", "o": ["Violin", "Trumpet (Kèn trumpet)", "Piano", "Flute"], "a": 1, "difficulty": 1},
    {"id": "music_009", "q": "'Bohemian Rhapsody' là bài hát nổi tiếng của ban nhạc nào?", "o": ["Led Zeppelin", "The Rolling Stones", "Queen", "Pink Floyd"], "a": 2, "difficulty": 1},
    {"id": "music_010", "q": "Dòng nhạc 'Hip-hop' bắt nguồn từ thành phố nào của Mỹ?", "o": ["Los Angeles", "Chicago", "Houston", "New York"], "a": 3, "difficulty": 2},
    {"id": "music_011", "q": "Adele nổi tiếng với giọng hát thuộc giọng nào?", "o": ["Soprano", "Mezzo-soprano", "Alto", "Contralto"], "a": 1, "difficulty": 2},
    {"id": "music_012", "q": "Nhạc cụ piano có bao nhiêu phím?", "o": ["72", "76", "88", "96"], "a": 2, "difficulty": 1},
    {"id": "music_013", "q": "Taylor Swift bắt đầu sự nghiệp âm nhạc với thể loại nào?", "o": ["Pop", "R&B", "Country", "Rock"], "a": 2, "difficulty": 1},
    {"id": "music_014", "q": "'Grammy Awards' trao giải cho lĩnh vực nào?", "o": ["Điện ảnh", "Âm nhạc", "Truyền hình", "Nghệ thuật sân khấu"], "a": 1, "difficulty": 1},
    {"id": "music_015", "q": "Nhạc sĩ nào được gọi là 'Ông hoàng nhạc Jazz'?", "o": ["Louis Armstrong", "Miles Davis", "Duke Ellington", "John Coltrane"], "a": 2, "difficulty": 2},
    {"id": "music_016", "q": "Bài 'Despacito' của Luis Fonsi đến từ quốc gia nào?", "o": ["Mexico", "Colombia", "Cuba", "Puerto Rico"], "a": 3, "difficulty": 1},
    {"id": "music_017", "q": "'Violin' thuộc họ nhạc cụ nào?", "o": ["Bộ gõ", "Bộ hơi", "Bộ dây kéo cung", "Bộ phím"], "a": 2, "difficulty": 1},
    {"id": "music_018", "q": "Ai sáng tác bản nhạc 'Für Elise'?", "o": ["Mozart", "Schubert", "Beethoven", "Brahms"], "a": 2, "difficulty": 1},
    {"id": "music_019", "q": "Nhóm nhạc nào nổi tiếng với bài 'Hotel California'?", "o": ["The Eagles", "Fleetwood Mac", "The Doors", "Creedence Clearwater"], "a": 0, "difficulty": 1},
    {"id": "music_020", "q": "'K-pop' là viết tắt của gì?", "o": ["Korean Popular Music", "Korean Pop Music", "Korea Pop", "Korean Power Music"], "a": 1, "difficulty": 1},
    {"id": "music_021", "q": "Nhạc cụ nào có dây được gẩy bằng tay?", "o": ["Violin", "Cello", "Harp (Đàn hạc)", "Double Bass"], "a": 2, "difficulty": 2},
    {"id": "music_022", "q": "'Spotify' là dịch vụ gì?", "o": ["Mạng xã hội", "Nền tảng xem phim", "Dịch vụ nghe nhạc trực tuyến", "Cửa hàng nhạc cụ"], "a": 2, "difficulty": 1},
    {"id": "music_023", "q": "Bài 'Happy Birthday' được sáng tác năm nào?", "o": ["1893", "1920", "1935", "1950"], "a": 0, "difficulty": 2},
    {"id": "music_024", "q": "Nhạc sĩ Việt Nam nào được coi là 'ông hoàng nhạc nhẹ'?", "o": ["Trịnh Công Sơn", "Ngô Thụy Miên", "Đức Huy", "Phú Quang"], "a": 1, "difficulty": 2},
    {"id": "music_025", "q": "Dòng nhạc 'EDM' là viết tắt của gì?", "o": ["Every Day Music", "Electronic Dance Music", "Extended Digital Music", "Easy Dance Mix"], "a": 1, "difficulty": 1},
    {"id": "music_026", "q": "Nhạc sĩ thiên tài người Áo, mất năm 35 tuổi là ai?", "o": ["Beethoven", "Schubert", "Mozart", "Brahms"], "a": 2, "difficulty": 2},
    {"id": "music_027", "q": "'Ukulele' là nhạc cụ bắt nguồn từ đâu?", "o": ["Nhật Bản", "Hawaii", "Philippines", "Polynesia"], "a": 1, "difficulty": 1},
    {"id": "music_028", "q": "Trong ký hiệu nhạc, 'forte' (f) có nghĩa là gì?", "o": ["Nhẹ nhàng", "To, mạnh", "Nhanh", "Chậm"], "a": 1, "difficulty": 1},
    {"id": "music_029", "q": "Ban nhạc 'ABBA' đến từ quốc gia nào?", "o": ["Na Uy", "Đan Mạch", "Phần Lan", "Thụy Điển"], "a": 3, "difficulty": 1},
    {"id": "music_030", "q": "Nhạc cụ nào là biểu tượng của âm nhạc truyền thống Việt Nam?", "o": ["Đàn guitar", "Đàn bầu", "Đàn piano", "Đàn violin"], "a": 1, "difficulty": 1},
    {"id": "music_031", "q": "'Reggae' là thể loại âm nhạc xuất xứ từ đâu?", "o": ["Nigeria", "Ghana", "Jamaica", "Trinidad"], "a": 2, "difficulty": 1},
    {"id": "music_032", "q": "Cặp đôi nhạc sĩ nào sáng tác opera 'The Marriage of Figaro'?", "o": ["Beethoven & Schiller", "Mozart & Da Ponte", "Verdi & Boito", "Puccini & Illica"], "a": 1, "difficulty": 3},
    {"id": "music_033", "q": "Nhạc sĩ người Việt nào nổi tiếng với dòng nhạc 'Tình ca quê hương'?", "o": ["Văn Cao", "Phạm Duy", "Trịnh Công Sơn", "Hoàng Việt"], "a": 1, "difficulty": 2},
    {"id": "music_034", "q": "'Bass guitar' thường có bao nhiêu dây?", "o": ["4", "5", "6", "3"], "a": 0, "difficulty": 1},
    {"id": "music_035", "q": "Nhạc sĩ Frédéric Chopin quốc tịch gì?", "o": ["Pháp", "Đức", "Áo", "Ba Lan"], "a": 3, "difficulty": 1},
    {"id": "music_036", "q": "'Bài Thánh ca buồn' là tác phẩm của nhạc sĩ Việt Nam nào?", "o": ["Trịnh Công Sơn", "Ngô Thụy Miên", "Vũ Thành An", "Lam Phương"], "a": 2, "difficulty": 2},
    {"id": "music_037", "q": "Nhạc sĩ nào được gọi là 'Ông vua nhạc Rock and Roll'?", "o": ["Chuck Berry", "Little Richard", "Elvis Presley", "Jerry Lee Lewis"], "a": 2, "difficulty": 1},
    {"id": "music_038", "q": "'Stradivarius' nổi tiếng là loại nhạc cụ gì?", "o": ["Piano", "Guitar", "Violin", "Cello"], "a": 2, "difficulty": 1},
    {"id": "music_039", "q": "Nhóm nhạc 'Blackpink' có bao nhiêu thành viên?", "o": ["3", "4", "5", "6"], "a": 1, "difficulty": 1},
    {"id": "music_040", "q": "Trong âm nhạc, 'tempo' chỉ điều gì?", "o": ["Âm lượng của bản nhạc", "Tốc độ/nhịp độ của bản nhạc", "Cao độ của nốt nhạc", "Sắc thái cảm xúc"], "a": 1, "difficulty": 1}
  ]
}